floods_html/__init__.py
floods_html/_version.py
floods_html/cli.py
floods_html/floods_html.py
floods_html/json_format.py
floods_html/styles/__init__.py
floods_html/styles/floods-html-global-seas-table.css
floods_html/styles/loader.py
floods_html/templates/seas_tables_styles.css.jinja
floods_html-0.5.0.dist-info/licenses/LICENSE
floods_html-0.5.0.dist-info/METADATA
floods_html-0.5.0.dist-info/WHEEL
floods_html-0.5.0.dist-info/entry_points.txt
floods_html-0.5.0.dist-info/top_level.txt
floods_html-0.5.0.dist-info/RECORD
