Metadata-Version: 2.4
Name: floods_html
Version: 0.5.0
Summary: Simplify JSON to HTML conversion
Author-email: Oisín Morrison <oisin.morrison@ecmwf.int>
License:                                  Apache License
Project-URL: repository, https://github.com/ecmwf/floods-html
Project-URL: issues, https://github.com/ecmwf/floods-html/issues
Classifier: Development Status :: 4 - Beta
Classifier: Intended Audience :: Science/Research
Classifier: License :: OSI Approved :: Apache Software License
Classifier: Natural Language :: English
Classifier: Operating System :: OS Independent
Classifier: Programming Language :: Python :: 3
Classifier: Programming Language :: Python :: 3 :: Only
Classifier: Programming Language :: Python :: 3.8
Classifier: Programming Language :: Python :: 3.10
Classifier: Topic :: Scientific/Engineering
Requires-Python: >=3.9
License-File: LICENSE
Requires-Dist: pydantic>=2
Requires-Dist: pydantic-extra-types
Requires-Dist: jinja2
Provides-Extra: test
Requires-Dist: pytest; extra == "test"
Requires-Dist: html5lib; extra == "test"
Requires-Dist: ipython; extra == "test"
Provides-Extra: dev
Requires-Dist: pytest; extra == "dev"
Requires-Dist: html5lib; extra == "dev"
Requires-Dist: ruff; extra == "dev"
Requires-Dist: pre-commit; extra == "dev"
Requires-Dist: jupyter; extra == "dev"
Dynamic: license-file
